AUTHORS.rst
LICENSE
MANIFEST.in
README.rst
pyproject.toml
setup.cfg
setup.py
tox.ini
jsonwebtoken/__init__.py
jsonwebtoken/algorithms.py
jsonwebtoken/api_jwk.py
jsonwebtoken/api_jws.py
jsonwebtoken/api_jwt.py
jsonwebtoken/exceptions.py
jsonwebtoken/help.py
jsonwebtoken/jwk_set_cache.py
jsonwebtoken/jwks_client.py
jsonwebtoken/py.typed
jsonwebtoken/utils.py
jsonwebtoken/warnings.py
jsonwebtoken.egg-info/PKG-INFO
jsonwebtoken.egg-info/SOURCES.txt
jsonwebtoken.egg-info/dependency_links.txt
jsonwebtoken.egg-info/not-zip-safe
jsonwebtoken.egg-info/requires.txt
jsonwebtoken.egg-info/top_level.txt
tests/__init__.py
tests/test_advisory.py
tests/test_algorithms.py
tests/test_api_jwk.py
tests/test_api_jws.py
tests/test_api_jwt.py
tests/test_exceptions.py
tests/test_jwks_client.py
tests/test_jwt.py
tests/test_utils.py
tests/utils.py
tests/keys/__init__.py
tests/keys/jwk_ec_key_P-256.json
tests/keys/jwk_ec_key_P-384.json
tests/keys/jwk_ec_key_P-521.json
tests/keys/jwk_ec_key_secp256k1.json
tests/keys/jwk_ec_pub_P-256.json
tests/keys/jwk_ec_pub_P-384.json
tests/keys/jwk_ec_pub_P-521.json
tests/keys/jwk_ec_pub_secp256k1.json
tests/keys/jwk_hmac.json
tests/keys/jwk_keyset_only_unknown_alg.json
tests/keys/jwk_keyset_with_unknown_alg.json
tests/keys/jwk_okp_key_Ed25519.json
tests/keys/jwk_okp_key_Ed448.json
tests/keys/jwk_okp_pub_Ed25519.json
tests/keys/jwk_okp_pub_Ed448.json
tests/keys/jwk_rsa_key.json
tests/keys/jwk_rsa_pub.json
tests/keys/testkey2_rsa.pub.pem
tests/keys/testkey_ec.priv
tests/keys/testkey_ec.pub
tests/keys/testkey_ec_secp192r1.priv
tests/keys/testkey_ec_ssh.pub
tests/keys/testkey_ed25519
tests/keys/testkey_ed25519.pub
tests/keys/testkey_pkcs1.pub.pem
tests/keys/testkey_rsa.cer
tests/keys/testkey_rsa.priv
tests/keys/testkey_rsa.pub